setup.py
janky_post/__init__.py
janky_post/gae.py
janky_post/tornado_handler.py
janky_post.egg-info/PKG-INFO
janky_post.egg-info/SOURCES.txt
janky_post.egg-info/dependency_links.txt
janky_post.egg-info/top_level.txt