Metadata-Version: 1.0
Name: janky-post
Version: 0.5
Summary: Makes janky cross-domain communication easy
Home-page: http://saunter.org/janky.post/
Author: Thomas Rampelberg
Author-email: thomas@saunter.org
License: UNKNOWN
Platform: UNKNOWN
